avg_laba4_9/__init__.py
avg_laba4_9/main.py
avg_laba4_9-0.1.0.dist-info/METADATA
avg_laba4_9-0.1.0.dist-info/WHEEL
avg_laba4_9-0.1.0.dist-info/licenses/LICENSE
avg_laba4_9-0.1.0.dist-info/RECORD
