Metadata-Version: 2.4
Name: avg_laba4_9
Version: 0.1.0
Summary: Simple package for difference of two numbers
Author-email: Your Name <your.email@example.com>
License: MIT
License-File: LICENSE
Requires-Python: >=3.6
